{
    "device_id": "esp32_air_monitor_1",
    "sensors": {
        "humidity": {
            "value": 50.0,
            "unit": "%"
        },
        "co": {
            "value": 0,
            "unit": "ppm"
        },
        "temperature": {
            "value": 25.0,
            "unit": "C"
        },
        "co2": {
            "value": 3506,
            "unit": "ppm"
        }
    },
    "air_quality": {
        "description": "MOYENNE",
        "score": 58
    },
    "timestamp": 799661459
}